{
  "name": "Horse",
  "fields": [
    {
      "fieldName": "name",
      "fieldType": "String",
      "fieldValidateRules": [
        "required"
      ]
    },
    {
      "fieldName": "ownerId",
      "fieldType": "Long"
    },
    {
      "fieldName": "gender",
      "fieldType": "Gender",
      "fieldValues": "MARE,STALLION,GELDING",
      "fieldValidateRules": [
        "required"
      ]
    },
    {
      "fieldName": "birth",
      "fieldType": "Instant"
    },
    {
      "fieldName": "colorId",
      "fieldType": "Long"
    }
  ],
  "relationships": [],
  "changelogDate": "20200604200807",
  "entityTableName": "horse",
  "dto": "no",
  "pagination": "no",
  "service": "no",
  "jpaMetamodelFiltering": false,
  "fluentMethods": true,
  "readOnly": false,
  "embedded": false,
  "clientRootFolder": "",
  "applications": "*"
}
